rc_robosim.libs/libode-6c6485ab.so.8.0.0
robosim/_robosim.cpython-38-x86_64-linux-gnu.so
robosim/__init__.py
rc_robosim-0.0.7.dist-info/RECORD
rc_robosim-0.0.7.dist-info/WHEEL
rc_robosim-0.0.7.dist-info/top_level.txt
rc_robosim-0.0.7.dist-info/METADATA
