Metadata-Version: 2.1
Name: rc-robosim
Version: 0.0.7
Summary: SSL and VSS robot soccer simulator
Home-page: https://github.com/robocin/rSim
Author: Felipe Martins
Author-email: fbm2@cin.ufpe.br
License: UNKNOWN
Platform: UNKNOWN
